aiconfig_extension_gemini/Gemini.py
aiconfig_extension_gemini/__init__.py
aiconfig_extension_gemini-0.0.5.dist-info/LICENSE
aiconfig_extension_gemini-0.0.5.dist-info/METADATA
aiconfig_extension_gemini-0.0.5.dist-info/WHEEL
aiconfig_extension_gemini-0.0.5.dist-info/top_level.txt
aiconfig_extension_gemini-0.0.5.dist-info/RECORD
